siri_question_answer-0.1.5.dist-info/METADATA
siri_question_answer-0.1.5.dist-info/WHEEL
siri_question_answer/__init__.py
siri_question_answer/siri_question_answer.cpython-312-darwin.so
siri_question_answer-0.1.5.dist-info/RECORD
