Metadata-Version: 2.4
Name: siri_question_answer
Version: 0.1.5
Classifier: Programming Language :: Rust
Classifier: Programming Language :: Python :: Implementation :: CPython
Classifier: Programming Language :: Python :: Implementation :: PyPy
Classifier: Development Status :: 4 - Beta
Summary: Python bindings for the siri_question_awnser Rust crate
Keywords: siri,question,awnser
Author-email: Prince Merveil ONDONDA <prince.ondonda@hove.com>
Maintainer-email: Prince Merveil ONDONDA <prince.ondonda@hove.com>
Requires-Python: >=3.8
